{
    "BTC": {
        "cmcId": 1,
        "fullname": "Bitcoin",
        "founder": "Satoshi Nakamoto",
        "card": "http://static.togetthere.cn/card_btc.png",
        "DOB": "2009-01-03",
        "color": "#ebd4b0",
        "textcolor": "#d48e18",
        "consensus": "PoW",
        "info": "In Nov. 2008, a guy named Satoshi Nakamoto announced his idea about cryptocurrency."
    },
    "ETH": {
        "cmcId": 1027,
        "fullname": "Ethereum",
        "founder": "Vitalik Buterin",
        "DOB": "",
        "card": "http://static.togetthere.cn/card_eth.png",
        "color": "#bbe7ae",
        "textcolor": "#59904c",
        "consensus": "PoS"
    },
    "DGC": {
        "cmcId": 74,
        "fullname": "Dogecoin",
        "color": "#e8c0af",
        "textcolor": "#b47a68",
        "founder": "Billy Markus",
        "DOB": "2013-12-06",
        "card": "http://static.togetthere.cn/card_doge.png",
        "consensus": "PoW"
    },
    "XPM": {
        "cmcId": 42,
        "card": "http://static.togetthere.cn/card_xpm.png",
        "fullname": "Primecoin",
        "founder": "Sunny King",
        "DOB": "2013-07-06",
        "consensus": "PoW",
        "color": "#ebe5b0",
        "textcolor": "#b8a909"
    },
    "SARI":{
        "id": -1,
        "fullname": "SARI",
        "color": "#aedfe8",
        "textcolor": "#3199af",
        "card": "http://static.togetthere.cn/card_sari.png"
    },
    "Blockchain":{
        "id": -1,
        "fullname": "Blockchain",
        "color": "#aec9e9",
        "textcolor": "#5381b7",
        "card": "http://static.togetthere.cn/card_block.png"
	}
}